ado_git_repo_insights/__init__.py
ado_git_repo_insights/cli.py
ado_git_repo_insights/config.py
ado_git_repo_insights/commands/__init__.py
ado_git_repo_insights/commands/doctor.py
ado_git_repo_insights/commands/setup_path.py
ado_git_repo_insights/extractor/__init__.py
ado_git_repo_insights/extractor/ado_client.py
ado_git_repo_insights/extractor/pagination.py
ado_git_repo_insights/extractor/pr_extractor.py
ado_git_repo_insights/ml/__init__.py
ado_git_repo_insights/ml/date_utils.py
ado_git_repo_insights/ml/fallback_forecaster.py
ado_git_repo_insights/ml/forecaster.py
ado_git_repo_insights/ml/insights.py
ado_git_repo_insights/persistence/__init__.py
ado_git_repo_insights/persistence/database.py
ado_git_repo_insights/persistence/models.py
ado_git_repo_insights/persistence/repository.py
ado_git_repo_insights/transform/__init__.py
ado_git_repo_insights/transform/aggregators.py
ado_git_repo_insights/transform/csv_generator.py
ado_git_repo_insights/ui_bundle/VSS.SDK.min.js
ado_git_repo_insights/ui_bundle/artifact-client.js
ado_git_repo_insights/ui_bundle/dashboard.js
ado_git_repo_insights/ui_bundle/dataset-loader.js
ado_git_repo_insights/ui_bundle/error-codes.js
ado_git_repo_insights/ui_bundle/error-types.js
ado_git_repo_insights/ui_bundle/index.html
ado_git_repo_insights/ui_bundle/settings.html
ado_git_repo_insights/ui_bundle/settings.js
ado_git_repo_insights/ui_bundle/styles.css
ado_git_repo_insights/utils/__init__.py
ado_git_repo_insights/utils/dataset_discovery.py
ado_git_repo_insights/utils/datetime_utils.py
ado_git_repo_insights/utils/install_detection.py
ado_git_repo_insights/utils/logging_config.py
ado_git_repo_insights/utils/path_utils.py
ado_git_repo_insights/utils/run_summary.py
ado_git_repo_insights/utils/safe_extract.py
ado_git_repo_insights/utils/shell_detection.py
ado_git_repo_insights/utils/ui_sync.py
ado_git_repo_insights-5.18.2.dist-info/licenses/LICENSE
ado_git_repo_insights-5.18.2.dist-info/METADATA
ado_git_repo_insights-5.18.2.dist-info/WHEEL
ado_git_repo_insights-5.18.2.dist-info/entry_points.txt
ado_git_repo_insights-5.18.2.dist-info/top_level.txt
ado_git_repo_insights-5.18.2.dist-info/RECORD
