Metadata-Version: 2.4
Name: ado-git-repo-insights
Version: 5.18.2
Summary: Extract Azure DevOps Pull Request metrics to SQLite and generate PowerBI-compatible CSVs.
Author-email: "Odd Essentials, LLC" <admin@oddessentials.com>
License: MIT
Classifier: Development Status :: 4 - Beta
Classifier: Intended Audience :: Developers
Classifier: License :: OSI Approved :: MIT License
Classifier: Programming Language :: Python :: 3
Classifier: Programming Language :: Python :: 3.10
Classifier: Programming Language :: Python :: 3.11
Classifier: Programming Language :: Python :: 3.12
Requires-Python: >=3.10
License-File: LICENSE
Requires-Dist: requests>=2.28.0
Requires-Dist: pyyaml>=6.0
Requires-Dist: pandas<3.0.0,>=2.2.0; python_version < "3.11"
Requires-Dist: pandas>=3.0.0; python_version >= "3.11"
Requires-Dist: azure-storage-blob>=12.0.0
Provides-Extra: dev
Requires-Dist: pytest>=7.0; extra == "dev"
Requires-Dist: pytest-cov>=4.0; extra == "dev"
Requires-Dist: ruff==0.14.14; extra == "dev"
Requires-Dist: mypy>=1.0; extra == "dev"
Requires-Dist: pre-commit>=3.0; extra == "dev"
Requires-Dist: types-requests>=2.28.0; extra == "dev"
Requires-Dist: types-PyYAML>=6.0; extra == "dev"
Requires-Dist: pandas-stubs<3.0.0,>=2.0.0; python_version < "3.11" and extra == "dev"
Requires-Dist: pandas-stubs>=2.0.0; python_version >= "3.11" and extra == "dev"
Requires-Dist: jsonschema>=4.0; extra == "dev"
Requires-Dist: defusedxml==0.7.1; extra == "dev"
Provides-Extra: ml
Requires-Dist: prophet>=1.1.0; extra == "ml"
Requires-Dist: openai>=1.0.0; extra == "ml"
Dynamic: license-file
